secoda_common/__init__.py
secoda_common/py.typed
secoda_common/log/__init__.py
secoda_common/log/action_log.py
secoda_common/log/action_log_callback.py
secoda_common/log/action_log_model.py
secoda_common/log/auth_caller_retrieval.py
secoda_common/log/caller_retrieval.py
secoda_common/log/http_header_caller_retrieval.py
secoda_common/models/__init__.py
secoda_common/models/dashboard.py
secoda_common/models/dictionary_term.py
secoda_common/models/event.py
secoda_common/models/index_map.py
secoda_common/models/integration.py
secoda_common/models/job.py
secoda_common/models/lineage.py
secoda_common/models/pii_table.py
secoda_common/models/popular_table.py
secoda_common/models/query.py
secoda_common/models/table.py
secoda_common/models/tag.py
secoda_common/models/user.py
secoda_common/tests/__init__.py
secoda_common/tests/fixtures.py
secoda_common/util/__init__.py
secoda_common/util/env.py
secoda_common/util/secure.py
secoda_common/util/validate.py
secoda_common-0.1.64.dist-info/METADATA
secoda_common-0.1.64.dist-info/WHEEL
secoda_common-0.1.64.dist-info/dependency_links.txt
secoda_common-0.1.64.dist-info/top_level.txt
secoda_common-0.1.64.dist-info/RECORD
